red_dead/__init__.py
red_dead/caching.py
red_dead/export.py
red_dead/gsheets.py
red_dead/items.py
red_dead/models.py
red_dead/sheet_transform.py
red_dead_tools-0.1.8.dist-info/LICENSE
red_dead_tools-0.1.8.dist-info/METADATA
red_dead_tools-0.1.8.dist-info/WHEEL
red_dead_tools-0.1.8.dist-info/top_level.txt
red_dead_tools-0.1.8.dist-info/RECORD
